{"id":"kevka","name":"Kevka","image":"images/player.png","classes":[],"metas":[],"timezone":"","card_content":[],"page_content":[],"discord":"","twitter":"","youtube":{"name":"","url":""},"twitch":{"name":"","url":""},"github":{"name":"","url":""},"teams":[],"records":[{"mode":"normal","episode":1,"meta":"gamecube","category":"3p","pb":true,"time":616,"players":[{"id":"kevka","class":"hucast","video":"","name":"Kevka"},{"id":"belz","class":"racast","video":"","name":"Belz"},{"id":"kayak","class":"fomar","video":"","name":"Kayak"}],"index":382,"quest":{"id":"ttf","name":"Towards the Future","is_countdown":false},"result":1,"team":null}],"record_count":1,"record_results":[null,1]}