{"id":"roo","name":"Roo","image":"images/player.png","classes":[],"metas":[],"timezone":"","card_content":[],"page_content":[],"discord":"","twitter":"","youtube":{"name":"","url":""},"twitch":{"name":"","url":""},"github":{"name":"","url":""},"teams":[],"records":[{"mode":"normal","episode":1,"meta":"vanilla","category":"opm","pb":false,"time":250,"players":[{"id":"roo","class":"ramar","video":"https://www.youtube.com/watch?v=E-atYq7zmR0","name":"Roo"}],"index":206,"quest":{"id":"max_forest","name":"Max: Forest","is_countdown":false},"result":1,"team":{"id":"pioneers","name":"Pioneers","image":"images/team_flags/pioneers.png"}},{"mode":"normal","episode":1,"meta":"vanilla","category":"4p","pb":false,"time":217,"players":[{"id":"travendus","class":"hunewearl","video":"","name":"Travendus"},{"id":"roo","class":"racast","video":"","name":"Roo"},{"id":"ayria","class":"ramarl","video":"","name":"Ayria"},{"id":"_shadofix","class":"fonewearl","video":"","name":"_shadowFIX"}],"index":209,"quest":{"id":"max_forest","name":"Max: Forest","is_countdown":false},"result":2,"team":null},{"mode":"normal","episode":1,"meta":"vanilla","category":"4p","pb":false,"time":243,"players":[{"id":"ender","class":"hucast","video":"","name":"Ender"},{"id":"travendus","class":"hucast","video":"","name":"Travendus"},{"id":"roo","class":"ramar","video":"","name":"Roo"},{"id":"stevecares","class":"fonewm","video":"","name":"SteveCares"}],"index":214,"quest":{"id":"max_caves","name":"Max: Caves","is_countdown":false},"result":2,"team":null},{"mode":"normal","episode":1,"meta":"vanilla","category":"opm","pb":false,"time":317,"players":[{"id":"roo","class":"racast","video":"https://www.youtube.com/watch?v=f9jrkn2V79g","name":"Roo"}],"index":219,"quest":{"id":"max_mines","name":"Max: Mines","is_countdown":false},"result":3,"team":{"id":"pioneers","name":"Pioneers","image":"images/team_flags/pioneers.png"}},{"mode":"normal","episode":1,"meta":"vanilla","category":"4p","pb":false,"time":270,"players":[{"id":"yuffie","class":"hunewearl","video":"","name":"Yuffie"},{"id":"roo","class":"racast","video":"","name":"Roo"},{"id":"eun-ji","class":"racaseal","video":"","name":"Eun-Ji"},{"id":"ender","class":"fonewearl","video":"","name":"Ender"}],"index":222,"quest":{"id":"max_mines","name":"Max: Mines","is_countdown":false},"result":3,"team":null},{"mode":"normal","episode":1,"meta":"vanilla","category":"opm","pb":false,"time":364,"players":[{"id":"roo","class":"racast","video":"","name":"Roo"}],"index":224,"quest":{"id":"max_ruins","name":"Max: Ruins","is_countdown":false},"result":2,"team":{"id":"pioneers","name":"Pioneers","image":"images/team_flags/pioneers.png"}},{"mode":"normal","episode":1,"meta":"vanilla","category":"4p","pb":false,"time":236,"players":[{"id":"travendus","class":"hucast","video":"","name":"Travendus"},{"id":"ender","class":"hucast","video":"https://www.youtube.com/watch?v=1GjL25hl1k4","name":"Ender"},{"id":"roo","class":"racast","video":"","name":"Roo"},{"id":"jajaswipo","class":"fonewm","video":"","name":"Jajaswipo"}],"index":228,"quest":{"id":"max_ruins","name":"Max: Ruins","is_countdown":false},"result":2,"team":null},{"mode":"normal","episode":1,"meta":"vanilla","category":"opm","pb":false,"time":380,"players":[{"id":"roo","class":"ramar","video":"https://www.youtube.com/watch?v=6c55Xhz474w","name":"Roo"}],"index":234,"quest":{"id":"mu1","name":"Mop-Up Operation #1","is_countdown":true},"result":5,"team":{"id":"pioneers","name":"Pioneers","image":"images/team_flags/pioneers.png"}},{"mode":"normal","episode":1,"meta":"vanilla","category":"opm","pb":false,"time":533,"players":[{"id":"roo","class":"ramarl","video":"https://www.youtube.com/watch?v=adwksxB9ix4","name":"Roo"}],"index":258,"quest":{"id":"ttf","name":"Towards the Future","is_countdown":false},"result":3,"team":{"id":"pioneers","name":"Pioneers","image":"images/team_flags/pioneers.png"}},{"mode":"normal","episode":1,"meta":"vanilla","category":"2p","pb":false,"time":546,"players":[{"id":"roo","class":"hucast","video":"","name":"Roo"},{"id":"ender","class":"hunewearl","video":"","name":"Ender"}],"index":269,"quest":{"id":"ttf","name":"Towards the Future","is_countdown":false},"result":4,"team":null},{"mode":"normal","episode":2,"meta":"vanilla","category":"opm","pb":false,"time":390,"players":[{"id":"roo","class":"ramar","video":"","name":"Roo"}],"index":288,"quest":{"id":"max_temple","name":"Max: Temple","is_countdown":false},"result":3,"team":{"id":"pioneers","name":"Pioneers","image":"images/team_flags/pioneers.png"}},{"mode":"normal","episode":2,"meta":"vanilla","category":"opm","pb":false,"time":268,"players":[{"id":"roo","class":"racaseal","video":"","name":"Roo"}],"index":292,"quest":{"id":"max_spaceship","name":"Max: Spaceship","is_countdown":false},"result":1,"team":{"id":"pioneers","name":"Pioneers","image":"images/team_flags/pioneers.png"}},{"mode":"normal","episode":2,"meta":"vanilla","category":"4p","pb":false,"time":334,"players":[{"id":"ender","class":"hucast","video":"","name":"Ender"},{"id":"travendus","class":"hucast","video":"","name":"Travendus"},{"id":"roo","class":"ramar","video":"","name":"Roo"},{"id":"stevecares","class":"fonewm","video":"","name":"SteveCares"}],"index":310,"quest":{"id":"max_tower","name":"Max: Tower","is_countdown":false},"result":2,"team":null},{"mode":"challenge","episode":1,"meta":"vanilla","category":"4p","pb":false,"time":394,"players":[{"id":"klekt","class":"hucast","video":"","name":"Klekt"},{"id":"mote","class":"hucast","video":"","name":"Mote"},{"id":"roo","class":"hucaseal","video":"","name":"Roo"},{"id":"capn","class":"fonewearl","video":"","name":"CAPN"}],"index":401,"quest":{"id":"1c1","name":"1C1","is_countdown":false},"result":1,"team":null},{"mode":"challenge","episode":1,"meta":"vanilla","category":"2p","pb":false,"time":479,"players":[{"id":"roo","class":"hucast","video":"","name":"Roo"},{"id":"capn","class":"hucast","video":"","name":"CAPN"}],"index":405,"quest":{"id":"1c1","name":"1C1","is_countdown":false},"result":2,"team":null},{"mode":"challenge","episode":1,"meta":"vanilla","category":"2p","pb":false,"time":1293,"players":[{"id":"roo","class":"hucast","video":"","name":"Roo"},{"id":"aerilas","class":"hucast","video":"","name":"Aerilas"}],"index":416,"quest":{"id":"1c3","name":"1C3","is_countdown":false},"result":1,"team":null},{"mode":"challenge","episode":1,"meta":"vanilla","category":"2p","pb":false,"time":1581,"players":[{"id":"roo","class":"hucast","video":"","name":"Roo"},{"id":"capn","class":"hucast","video":"","name":"CAPN"}],"index":421,"quest":{"id":"1c4","name":"1C4","is_countdown":false},"result":1,"team":null},{"mode":"challenge","episode":1,"meta":"vanilla","category":"2p","pb":false,"time":1884,"players":[{"id":"roo","class":"hucast","video":"","name":"Roo"},{"id":"spuz","class":"fonewm","video":"https://youtu.be/B4O5mMS3y70","name":"Spuz"}],"index":423,"quest":{"id":"1c4","name":"1C4","is_countdown":false},"result":3,"team":null},{"mode":"challenge","episode":1,"meta":"vanilla","category":"2p","pb":false,"time":2275,"players":[{"id":"roo","class":"hucast","video":"","name":"Roo"},{"id":"schranko","class":"fonewearl","video":"","name":"Schranko"}],"index":424,"quest":{"id":"1c4","name":"1C4","is_countdown":false},"result":4,"team":null},{"mode":"challenge","episode":1,"meta":"vanilla","category":"2p","pb":false,"time":1183,"players":[{"id":"roo","class":"hucast","video":"","name":"Roo"},{"id":"aerilas","class":"hucast","video":"","name":"Aerilas"}],"index":428,"quest":{"id":"1c5","name":"1C5","is_countdown":false},"result":1,"team":null},{"mode":"challenge","episode":1,"meta":"vanilla","category":"2p","pb":false,"time":1578,"players":[{"id":"roo","class":"hucast","video":"","name":"Roo"},{"id":"nohit","class":"ramar","video":"","name":"NoHit"}],"index":429,"quest":{"id":"1c5","name":"1C5","is_countdown":false},"result":2,"team":null},{"mode":"challenge","episode":1,"meta":"vanilla","category":"2p","pb":false,"time":1779,"players":[{"id":"roo","class":"hucast","video":"","name":"Roo"},{"id":"aerilas","class":"hucast","video":"","name":"Aerilas"}],"index":436,"quest":{"id":"1c7","name":"1C7","is_countdown":false},"result":1,"team":null},{"mode":"challenge","episode":1,"meta":"vanilla","category":"4p","pb":false,"time":1674,"players":[{"id":"spuz","class":"hucast","video":"","name":"Spuz"},{"id":"dj_ridoo","class":"hucast","video":"","name":"DJ Ridoo"},{"id":"no_future","class":"hucast","video":"","name":"No Future"},{"id":"roo","class":"hucaseal","video":"","name":"Roo"}],"index":440,"quest":{"id":"1c8","name":"1C8","is_countdown":false},"result":3,"team":null},{"mode":"challenge","episode":1,"meta":"vanilla","category":"4p","pb":false,"time":1708,"players":[{"id":"schranko","class":"hucast","video":"","name":"Schranko"},{"id":"uno","class":"hucast","video":"","name":"Uno"},{"id":"roo","class":"hucaseal","video":"","name":"Roo"},{"id":"spuz","class":"fonewm","video":"","name":"Spuz"}],"index":442,"quest":{"id":"1c8","name":"1C8","is_countdown":false},"result":5,"team":null},{"mode":"challenge","episode":1,"meta":"vanilla","category":"2p","pb":false,"time":2109,"players":[{"id":"roo","class":"hucast","video":"","name":"Roo"},{"id":"aerilas","class":"hucast","video":"","name":"Aerilas"}],"index":443,"quest":{"id":"1c8","name":"1C8","is_countdown":false},"result":1,"team":null},{"mode":"challenge","episode":1,"meta":"vanilla","category":"3p","pb":false,"time":2455,"players":[{"id":"roo","class":"hucast","video":"","name":"Roo"},{"id":"vex","class":"fonewearl","video":"","name":"Vex"},{"id":"spuz","class":"fonewearl","video":"","name":"Spuz"}],"index":451,"quest":{"id":"1c9","name":"1C9","is_countdown":false},"result":1,"team":null}],"record_count":26,"record_results":[null,9,7,6,2,2]}