{"id":"tom","name":"Tom","image":"images/player.png","classes":[],"metas":[],"timezone":"","card_content":[],"page_content":[],"discord":"","twitter":"","youtube":{"name":"","url":""},"twitch":{"name":"","url":""},"github":{"name":"","url":""},"teams":[],"records":[{"mode":"normal","episode":1,"meta":"gamecube","category":"4p","pb":false,"time":371,"players":[{"id":"armand","class":"hucast","video":"","name":"Armand"},{"id":"9898","class":"hucast","video":"","name":"9898"},{"id":"tom","class":"hucast","video":"","name":"Tom"},{"id":"belz","class":"hunewearl","video":"","name":"Belz"}],"index":371,"quest":{"id":"mu1","name":"Mop-Up Operation #1","is_countdown":true},"result":1,"team":null},{"mode":"normal","episode":1,"meta":"gamecube","category":"4p","pb":false,"time":583,"players":[{"id":"belz","class":"hucast","video":"","name":"Belz"},{"id":"tom","class":"hucast","video":"","name":"Tom"},{"id":"armand","class":"hucast","video":"","name":"Armand"},{"id":"ambrosia","class":"ramarl","video":"","name":"Ambrosia"}],"index":381,"quest":{"id":"mu4","name":"Mop-Up Operation #4","is_countdown":true},"result":3,"team":null},{"mode":"normal","episode":1,"meta":"gamecube","category":"4p","pb":false,"time":352,"players":[{"id":"belz","class":"hucast","video":"","name":"Belz"},{"id":"armand","class":"hucast","video":"","name":"Armand"},{"id":"chi","class":"ramarl","video":"","name":"Chi"},{"id":"tom","class":"fomar","video":"","name":"Tom"}],"index":388,"quest":{"id":"fragments_of_a_memory","name":"Fragments of a Memory","is_countdown":false},"result":1,"team":null}],"record_count":3,"record_results":[null,2,null,1]}